{
  "easy": [
    {
      "id": "e1",
      "title": "破碎的玻璃杯",
      "situation": "地上有一个破碎的玻璃杯和一滩水。",
      "truth": "一只猫从桌子上推下了装满水的玻璃杯。",
      "background": "这是一个普通的下午，家里养的猫在桌子上玩耍时不小心碰倒了玻璃杯。",
      "hints": [
        "想想还有谁/什么可能在场",
        "考虑一下重力的作用",
        "家里可能养了宠物"
      ]
    }
  ],
  "medium": [
    {
      "id": "m1",
      "title": "深夜的敲门声",
      "situation": "深夜，一个人听到敲门声后打开门，却发现门外空无一人。",
      "truth": "这是一个送外卖的人敲错了门，意识到后迅速去了隔壁正确的门牌号。",
      "background": "这发生在一个下着小雨的夜晚，送外卖的人因为雨水模糊了视线，一时看错了门牌号。",
      "hints": [
        "考虑这个时间点可能发生的事情",
        "现代生活中的一些服务",
        "天气可能影响了什么"
      ]
    }
  ],
  "hard": [
    {
      "id": "h1",
      "title": "消失的钥匙",
      "situation": "一个人早上醒来发现放在床头柜上的钥匙不见了，房间的门窗都是锁着的。",
      "truth": "空调制冷时产生的冷凝水滴在钥匙上，钥匙顺着水滴滑落到了床头柜后面的缝隙中。",
      "background": "这是一个炎热的夏夜，房间开着空调睡觉。空调产生的冷凝水顺着墙面流下，正好滴在钥匙上。",
      "hints": [
        "关注房间的温度变化",
        "想想水从哪里来",
        "物体可能的运动方向"
      ]
    }
  ],
  "hell": [
    {
      "id": "x1",
      "title": "午夜的电话",
      "situation": "深夜12点，一个人接到一通电话，电话那头只有沙沙声，挂断后手机显示没有任何通话记录。",
      "truth": "这个人在熬夜工作时不小心睡着了，梦到了电话响。手机确实没有任何通话记录，因为这只是一个梦。",
      "background": "这个人因为工作压力很大，经常熬夜。那天他在电脑前工作到深夜，不知不觉睡着了。",
      "hints": [
        "考虑人的生理状态",
        "现实和梦境的区别",
        "为什么没有通话记录"
      ]
    }
  ]
} 